a2lparser/__init__.py
a2lparser/a2l_parser.py
pya2lparser-0.0.1.dist-info/licenses/LICENSE
pya2lparser-0.0.1.dist-info/METADATA
pya2lparser-0.0.1.dist-info/WHEEL
pya2lparser-0.0.1.dist-info/top_level.txt
pya2lparser-0.0.1.dist-info/RECORD
