Metadata-Version: 2.4
Name: PyA2lParser
Version: 0.0.1
Summary: Parse ASAP2 A2L file
Home-page: https://github.com/sgnes/A2l-Parser
Author: Sgnes
Author-email: sgnes0514@gmai.com
Classifier: Programming Language :: Python :: 3
Classifier: License :: OSI Approved :: MIT License
Classifier: Operating System :: OS Independent
Requires-Python: >=3.8
License-File: LICENSE
Dynamic: author
Dynamic: author-email
Dynamic: classifier
Dynamic: description
Dynamic: description-content-type
Dynamic: home-page
Dynamic: license-file
Dynamic: requires-python
Dynamic: summary
